	[
		{
			"constant": false,
			"inputs": [
				{
					"name": "user_addresss",
					"type": "address"
				},
				{
					"name": "value",
					"type": "uint256"
				}
			],
			"name": "award",
			"outputs": [],
			"payable": false,
			"stateMutability": "nonpayable",
			"type": "function"
		},
		{
			"constant": false,
			"inputs": [
				{
					"name": "user_addresss",
					"type": "address"
				},
				{
					"name": "value",
					"type": "uint256"
				}
			],
			"name": "bet",
			"outputs": [],
			"payable": false,
			"stateMutability": "nonpayable",
			"type": "function"
		},
		{
			"constant": false,
			"inputs": [
				{
					"name": "value",
					"type": "uint256"
				}
			],
			"name": "devBonus",
			"outputs": [],
			"payable": false,
			"stateMutability": "nonpayable",
			"type": "function"
		},
		{
			"constant": false,
			"inputs": [
				{
					"name": "gameNumber",
					"type": "uint256"
				}
			],
			"name": "dice",
			"outputs": [
				{
					"name": "",
					"type": "bool"
				}
			],
			"payable": true,
			"stateMutability": "payable",
			"type": "function"
		},
		{
			"constant": false,
			"inputs": [],
			"name": "increaseGameNumber",
			"outputs": [],
			"payable": false,
			"stateMutability": "nonpayable",
			"type": "function"
		},
		{
			"anonymous": false,
			"inputs": [
				{
					"indexed": false,
					"name": "user_addresss",
					"type": "address"
				},
				{
					"indexed": false,
					"name": "value",
					"type": "uint256"
				},
				{
					"indexed": false,
					"name": "game_number",
					"type": "uint256"
				},
				{
					"indexed": false,
					"name": "game_name",
					"type": "string"
				}
			],
			"name": "AwardLog",
			"type": "event"
		},
		{
			"anonymous": false,
			"inputs": [
				{
					"indexed": false,
					"name": "user_addresss",
					"type": "address"
				},
				{
					"indexed": false,
					"name": "value",
					"type": "uint256"
				},
				{
					"indexed": false,
					"name": "game_number",
					"type": "uint256"
				},
				{
					"indexed": false,
					"name": "game_name",
					"type": "string"
				}
			],
			"name": "BetLog",
			"type": "event"
		},
		{
			"anonymous": false,
			"inputs": [
				{
					"indexed": false,
					"name": "player",
					"type": "address"
				},
				{
					"indexed": false,
					"name": "first",
					"type": "uint256"
				},
				{
					"indexed": false,
					"name": "second",
					"type": "uint256"
				}
			],
			"name": "Dice",
			"type": "event"
		},
		{
			"anonymous": false,
			"inputs": [
				{
					"indexed": false,
					"name": "dev_address",
					"type": "address"
				},
				{
					"indexed": false,
					"name": "value",
					"type": "uint256"
				},
				{
					"indexed": false,
					"name": "game_number",
					"type": "uint256"
				},
				{
					"indexed": false,
					"name": "game_name",
					"type": "string"
				}
			],
			"name": "BonusLog",
			"type": "event"
		},
		{
			"anonymous": false,
			"inputs": [
				{
					"indexed": false,
					"name": "user_addresss",
					"type": "address"
				},
				{
					"indexed": false,
					"name": "value",
					"type": "uint256"
				},
				{
					"indexed": false,
					"name": "game_number",
					"type": "uint256"
				},
				{
					"indexed": false,
					"name": "game_name",
					"type": "string"
				}
			],
			"name": "RefundLog",
			"type": "event"
		},
		{
			"anonymous": false,
			"inputs": [
				{
					"indexed": true,
					"name": "previousOwner",
					"type": "address"
				},
				{
					"indexed": true,
					"name": "newOwner",
					"type": "address"
				}
			],
			"name": "OwnershipTransferred",
			"type": "event"
		},
		{
			"constant": false,
			"inputs": [
				{
					"name": "user_addresss",
					"type": "address"
				},
				{
					"name": "value",
					"type": "uint256"
				}
			],
			"name": "refund",
			"outputs": [],
			"payable": false,
			"stateMutability": "nonpayable",
			"type": "function"
		},
		{
			"constant": false,
			"inputs": [
				{
					"name": "_name",
					"type": "string"
				}
			],
			"name": "setGameName",
			"outputs": [],
			"payable": false,
			"stateMutability": "nonpayable",
			"type": "function"
		},
		{
			"constant": false,
			"inputs": [
				{
					"name": "_number",
					"type": "uint256"
				}
			],
			"name": "setGameNumber",
			"outputs": [],
			"payable": false,
			"stateMutability": "nonpayable",
			"type": "function"
		},
		{
			"constant": false,
			"inputs": [
				{
					"name": "newOwner",
					"type": "address"
				}
			],
			"name": "transferOwnership",
			"outputs": [],
			"payable": false,
			"stateMutability": "nonpayable",
			"type": "function"
		},
		{
			"payable": true,
			"stateMutability": "payable",
			"type": "fallback"
		},
		{
			"inputs": [],
			"payable": true,
			"stateMutability": "payable",
			"type": "constructor"
		},
		{
			"constant": true,
			"inputs": [
				{
					"name": "",
					"type": "uint256"
				},
				{
					"name": "",
					"type": "uint256"
				}
			],
			"name": "diceInfos",
			"outputs": [
				{
					"name": "user",
					"type": "address"
				},
				{
					"name": "first",
					"type": "uint256"
				},
				{
					"name": "second",
					"type": "uint256"
				}
			],
			"payable": false,
			"stateMutability": "view",
			"type": "function"
		},
		{
			"constant": true,
			"inputs": [],
			"name": "fee",
			"outputs": [
				{
					"name": "",
					"type": "uint256"
				}
			],
			"payable": false,
			"stateMutability": "view",
			"type": "function"
		},
		{
			"constant": true,
			"inputs": [],
			"name": "game_name",
			"outputs": [
				{
					"name": "",
					"type": "string"
				}
			],
			"payable": false,
			"stateMutability": "view",
			"type": "function"
		},
		{
			"constant": true,
			"inputs": [],
			"name": "game_number",
			"outputs": [
				{
					"name": "",
					"type": "uint256"
				}
			],
			"payable": false,
			"stateMutability": "view",
			"type": "function"
		},
		{
			"constant": true,
			"inputs": [
				{
					"name": "gameNumber",
					"type": "uint256"
				}
			],
			"name": "getDiceCount",
			"outputs": [
				{
					"name": "",
					"type": "uint256"
				}
			],
			"payable": false,
			"stateMutability": "view",
			"type": "function"
		},
		{
			"constant": true,
			"inputs": [],
			"name": "owner",
			"outputs": [
				{
					"name": "",
					"type": "address"
				}
			],
			"payable": false,
			"stateMutability": "view",
			"type": "function"
		},
		{
			"constant": true,
			"inputs": [],
			"name": "prizePool",
			"outputs": [
				{
					"name": "",
					"type": "uint256"
				}
			],
			"payable": false,
			"stateMutability": "view",
			"type": "function"
		},
		{
			"constant": true,
			"inputs": [
				{
					"name": "",
					"type": "address"
				},
				{
					"name": "",
					"type": "uint256"
				}
			],
			"name": "userInfos",
			"outputs": [
				{
					"name": "gameNumber",
					"type": "uint256"
				},
				{
					"name": "first",
					"type": "uint256"
				},
				{
					"name": "second",
					"type": "uint256"
				}
			],
			"payable": false,
			"stateMutability": "view",
			"type": "function"
		}
	]
